tinc/__init__.py
tinc/cachemanager.py
tinc/client.py
tinc/datapool.py
tinc/disk_buffer.py
tinc/distributed_path.py
tinc/message.py
tinc/parameter.py
tinc/parameter_server.py
tinc/parameter_space.py
tinc/preset_handler.py
tinc/process_args.py
tinc/processor.py
tinc/tinc_cache_schema.json
tinc/tinc_client.py
tinc/tinc_object.py
tinc/tinc_protocol_pb2.py
tinc/variant.py
tinc_testing-0.9.33.7.dist-info/LICENSE
tinc_testing-0.9.33.7.dist-info/METADATA
tinc_testing-0.9.33.7.dist-info/WHEEL
tinc_testing-0.9.33.7.dist-info/top_level.txt
tinc_testing-0.9.33.7.dist-info/RECORD
