Metadata-Version: 2.1
Name: tinc-testing
Version: 0.9.33.7
Summary: TINC python module
Home-page: https://github.com/AlloSphere-Research-Group/tinc-python
Author: Andres Cabrera
Author-email: mantaraya36@gmail.com
License: UNKNOWN
Platform: UNKNOWN
Classifier: Programming Language :: Python :: 3
Classifier: License :: OSI Approved :: BSD License
Classifier: Operating System :: OS Independent
Requires-Python: >=3.6
Requires-Dist: numpy
Requires-Dist: matplotlib
Requires-Dist: filelock
Requires-Dist: netcdf4
Requires-Dist: jsonschema
Requires-Dist: protobuf
Requires-Dist: Pillow
